pms/__init__.py
pms/config.py
pms/final_transforming.py
pms/main.py
pms/tools.py
pms/env/DEFAULT.env
pms/import_worker/__init__.py
pms/import_worker/filter.py
pms/import_worker/parser.py
pms/import_worker/pubmed_source_file_handler.py
pms/import_worker/worker.py
PubMedSucker-1.5.13.dist-info/METADATA
PubMedSucker-1.5.13.dist-info/WHEEL
PubMedSucker-1.5.13.dist-info/top_level.txt
PubMedSucker-1.5.13.dist-info/RECORD
