Metadata-Version: 2.1
Name: PubMedSucker
Version: 1.5.13
Summary: Pull all articles from PubMed and insert them into a Neo4j Graph Database
Home-page: https://git.connect.dzd-ev.de/dzdtools/pubmedsucker
Author: TB
Author-email: tim.bleimehl@helmholtz-muenchen.de
License: MIT
Platform: UNKNOWN
Requires-Python: >=3.9
Requires-Dist: py2neo
Requires-Dist: lxml
Requires-Dist: xmltodict
Requires-Dist: memoization
Requires-Dist: graphio
Requires-Dist: neobulkmp
Requires-Dist: getversion
Requires-Dist: dict2graph (==2.0.0)
Requires-Dist: DZDConfigs
Requires-Dist: FTPDownloader
Requires-Dist: DZDutils
Requires-Dist: requests
Requires-Dist: py-expression-eval
